{
  "users": [
    {
      "id": 1,
      "firstname": "Mackenzie",
      "lastname": "Hodges",
      "age": 11
    },
    {
      "id": 2,
      "firstname": "Aaliyah",
      "lastname": "Hailey",
      "age": 12
    },
    {
      "id": 3,
      "firstname": "Lillian",
      "lastname": "Goodman",
      "age": 13
    },
    {
      "id": 4,
      "firstname": "Gabrielle",
      "lastname": "Warren",
      "age": 33
    },
    {
      "id": 5,
      "firstname": "Layla",
      "lastname": "Ogden",
      "age": 33
    },
    {
      "id": 6,
      "firstname": "Maya",
      "lastname": "Turner",
      "age": 33
    },
    {
      "id": 7,
      "firstname": "Brooklyn",
      "lastname": "Oldridge",
      "age": 33
    },
    {
      "id": 8,
      "firstname": "Brooklyn",
      "lastname": "Fulton",
      "age": 33
    },
    {
      "id": 9,
      "firstname": "Isabella",
      "lastname": "Gate",
      "age": 33
    },
    {
      "id": 11,
      "firstname": "Jocelyn",
      "lastname": "Oldman",
      "age": 33
    },
    {
      "id": 12,
      "firstname": "Gianna",
      "lastname": "Conors",
      "age": 33
    },
    {
      "id": 13,
      "firstname": "Destiny",
      "lastname": "Conors",
      "age": 33
    },
    {
      "id": 14,
      "firstname": "Sophie",
      "lastname": "Ford",
      "age": 33
    },
    {
      "id": 15,
      "firstname": "Serenity",
      "lastname": "Molligan",
      "age": 33
    },
    {
      "id": 16,
      "firstname": "Makayla",
      "lastname": "Ford",
      "age": 33
    },
    {
      "id": 17,
      "firstname": "Melanie",
      "lastname": "Sherlock",
      "age": 33
    },
    {
      "firstname": "saban",
      "lastname": "uenlue",
      "age": 44,
      "id": 18
    }
  ]
}